sqlite_utils_dateutil.py
sqlite_utils_dateutil-0.1.dist-info/LICENSE
sqlite_utils_dateutil-0.1.dist-info/METADATA
sqlite_utils_dateutil-0.1.dist-info/WHEEL
sqlite_utils_dateutil-0.1.dist-info/entry_points.txt
sqlite_utils_dateutil-0.1.dist-info/top_level.txt
sqlite_utils_dateutil-0.1.dist-info/RECORD
