Metadata-Version: 2.1
Name: sqlite-utils-dateutil
Version: 0.1
Summary: Date utility functions for sqlite-utils
Author: Simon Willison
License: Apache-2.0
Project-URL: Homepage, https://github.com/simonw/sqlite-utils-dateutil
Project-URL: Changelog, https://github.com/simonw/sqlite-utils-dateutil/releases
Project-URL: Issues, https://github.com/simonw/sqlite-utils-dateutil/issues
Project-URL: CI, https://github.com/simonw/sqlite-utils-dateutil/actions
Classifier: License :: OSI Approved :: Apache Software License
License-File: LICENSE
Requires-Dist: sqlite-utils
Provides-Extra: test
Requires-Dist: pytest ; extra == 'test'
